{
    "latitude": 20.700005,
    "longitude": -75.2,
    "generationtime_ms": 0.6860494613647461,
    "utc_offset_seconds": 0,
    "timezone": "GMT",
    "timezone_abbreviation": "GMT",
    "elevation": 0.0,
    "hourly_units": {
        "time": "iso8601",
        "temperature_2m": "°C",
        "relativehumidity_2m": "%",
        "dewpoint_2m": "°C",
        "apparent_temperature": "°C",
        "precipitation": "mm",
        "rain": "mm",
        "snowfall": "cm",
        "snow_depth": "m",
        "weathercode": "wmo code",
        "pressure_msl": "hPa",
        "surface_pressure": "hPa",
        "cloudcover": "%",
        "cloudcover_low": "%",
        "cloudcover_mid": "%",
        "cloudcover_high": "%",
        "et0_fao_evapotranspiration": "mm",
        "vapor_pressure_deficit": "kPa",
        "windspeed_10m": "km/h",
        "windspeed_100m": "km/h",
        "winddirection_10m": "°",
        "winddirection_100m": "°",
        "windgusts_10m": "km/h",
        "soil_temperature_0_to_7cm": "°C",
        "soil_temperature_7_to_28cm": "°C",
        "soil_temperature_28_to_100cm": "°C",
        "soil_temperature_100_to_255cm": "°C",
        "soil_moisture_0_to_7cm": "m³/m³",
        "soil_moisture_7_to_28cm": "m³/m³",
        "soil_moisture_28_to_100cm": "m³/m³",
        "soil_moisture_100_to_255cm": "m³/m³"
    },
    "hourly": {
        "time": [
            "2012-08-25T00:00",
            "2012-08-25T01:00",
            "2012-08-25T02:00",
            "2012-08-25T03:00",
            "2012-08-25T04:00",
            "2012-08-25T05:00",
            "2012-08-25T06:00",
            "2012-08-25T07:00",
            "2012-08-25T08:00",
            "2012-08-25T09:00",
            "2012-08-25T10:00",
            "2012-08-25T11:00",
            "2012-08-25T12:00",
            "2012-08-25T13:00",
            "2012-08-25T14:00",
            "2012-08-25T15:00",
            "2012-08-25T16:00",
            "2012-08-25T17:00",
            "2012-08-25T18:00",
            "2012-08-25T19:00",
            "2012-08-25T20:00",
            "2012-08-25T21:00",
            "2012-08-25T22:00",
            "2012-08-25T23:00"
        ],
        "temperature_2m": [
            28.9,
            28.9,
            28.6,
            28.5,
            28.4,
            28.6,
            28.2,
            28.0,
            27.3,
            27.3,
            27.4,
            27.2,
            27.0,
            26.8,
            26.7,
            27.2,
            27.7,
            27.3,
            27.2,
            27.2,
            27.5,
            27.4,
            27.3,
            26.8
        ],
        "relativehumidity_2m": [
            76,
            75,
            78,
            80,
            80,
            78,
            81,
            84,
            87,
            89,
            87,
            89,
            88,
            90,
            88,
            89,
            86,
            88,
            87,
            87,
            86,
            85,
            85,
            86
        ],
        "dewpoint_2m": [
            24.2,
            24.0,
            24.5,
            24.8,
            24.7,
            24.4,
            24.6,
            25.0,
            24.9,
            25.4,
            25.1,
            25.2,
            24.8,
            25.0,
            24.5,
            25.2,
            25.2,
            25.1,
            24.8,
            24.8,
            24.9,
            24.7,
            24.6,
            24.2
        ],
        "apparent_temperature": [
            30.7,
            30.4,
            30.3,
            30.4,
            30.7,
            30.9,
            30.5,
            30.4,
            29.6,
            30.3,
            31.5,
            30.6,
            29.9,
            30.2,
            29.9,
            31.2,
            32.7,
            32.5,
            31.4,
            31.7,
            31.3,
            31.3,
            31.2,
            30.3
        ],
        "precipitation": [
            0.0,
            0.0,
            0.0,
            0.0,
            0.0,
            0.1,
            0.2,
            0.1,
            0.7,
            1.5,
            0.8,
            1.1,
            0.9,
            2.5,
            3.3,
            3.5,
            1.1,
            0.6,
            2.0,
            0.1,
            1.5,
            1.8,
            1.1,
            0.9
        ],
        "rain": [
            0.0,
            0.0,
            0.0,
            0.0,
            0.0,
            0.1,
            0.2,
            0.1,
            0.7,
            1.5,
            0.8,
            1.1,
            0.9,
            2.5,
            3.3,
            3.5,
            1.1,
            0.6,
            2.0,
            0.1,
            1.5,
            1.8,
            1.1,
            0.9
        ],
        "snowfall": [
            0.0,
            0.0,
            0.0,
            0.0,
            0.0,
            0.0,
            0.0,
            0.0,
            0.0,
            0.0,
            0.0,
            0.0,
            0.0,
            0.0,
            0.0,
            0.0,
            0.0,
            0.0,
            0.0,
            0.0,
            0.0,
            0.0,
            0.0,
            0.0
        ],
        "snow_depth": [
            null,
            null,
            null,
            null,
            null,
            null,
            null,
            null,
            null,
            null,
            null,
            null,
            null,
            null,
            null,
            null,
            null,
            null,
            null,
            null,
            null,
            null,
            null,
            null
        ],
        "weathercode": [
            3,
            2,
            2,
            2,
            3,
            51,
            51,
            51,
            53,
            61,
            53,
            55,
            53,
            63,
            63,
            63,
            55,
            53,
            61,
            51,
            61,
            61,
            55,
            53
        ],
        "pressure_msl": [
            1006.7,
            1007.0,
            1007.0,
            1007.3,
            1007.3,
            1006.9,
            1006.1,
            1005.5,
            1005.4,
            1004.7,
            1005.1,
            1005.0,
            1005.9,
            1005.9,
            1004.8,
            1003.3,
            1002.4,
            1001.9,
            1000.9,
            1000.6,
            1001.7,
            1002.7,
            1003.2,
            1004.2
        ],
        "surface_pressure": [
            1006.7,
            1007.0,
            1007.0,
            1007.3,
            1007.3,
            1006.9,
            1006.1,
            1005.5,
            1005.4,
            1004.7,
            1005.1,
            1005.0,
            1005.9,
            1005.9,
            1004.8,
            1003.3,
            1002.4,
            1001.9,
            1000.9,
            1000.6,
            1001.7,
            1002.7,
            1003.2,
            1004.2
        ],
        "cloudcover": [
            97,
            77,
            60,
            73,
            100,
            100,
            92,
            76,
            95,
            100,
            68,
            100,
            100,
            100,
            100,
            100,
            100,
            90,
            80,
            83,
            100,
            100,
            100,
            88
        ],
        "cloudcover_low": [
            31,
            26,
            33,
            36,
            31,
            42,
            46,
            33,
            51,
            66,
            23,
            55,
            36,
            25,
            46,
            55,
            36,
            27,
            22,
            10,
            28,
            27,
            24,
            0
        ],
        "cloudcover_mid": [
            65,
            40,
            0,
            18,
            72,
            58,
            34,
            28,
            33,
            53,
            30,
            53,
            93,
            95,
            71,
            94,
            72,
            62,
            52,
            74,
            82,
            97,
            99,
            97
        ],
        "cloudcover_high": [
            100,
            100,
            100,
            100,
            99,
            100,
            100,
            100,
            98,
            100,
            98,
            73,
            91,
            94,
            97,
            98,
            98,
            95,
            98,
            99,
            100,
            100,
            100,
            100
        ],
        "et0_fao_evapotranspiration": [
            0.12,
            0.11,
            0.09,
            0.08,
            0.08,
            0.08,
            0.07,
            0.06,
            0.05,
            0.03,
            0.03,
            0.05,
            0.07,
            0.08,
            0.1,
            0.09,
            0.24,
            0.13,
            0.18,
            0.39,
            0.26,
            0.15,
            0.09,
            0.06
        ],
        "vapor_pressure_deficit": [
            0.97,
            1.0,
            0.85,
            0.76,
            0.76,
            0.86,
            0.73,
            0.62,
            0.49,
            0.38,
            0.46,
            0.4,
            0.42,
            0.37,
            0.42,
            0.4,
            0.51,
            0.45,
            0.48,
            0.48,
            0.51,
            0.54,
            0.54,
            0.5
        ],
        "windspeed_10m": [
            30.3,
            31.1,
            32.2,
            31.5,
            29.0,
            27.5,
            27.9,
            29.7,
            29.6,
            26.8,
            18.5,
            22.9,
            24.8,
            23.0,
            21.9,
            18.8,
            12.9,
            11.0,
            16.3,
            16.2,
            19.3,
            18.0,
            17.4,
            18.8
        ],
        "windspeed_100m": [
            43.3,
            44.4,
            46.0,
            45.3,
            40.9,
            39.0,
            39.9,
            42.8,
            41.9,
            38.1,
            27.4,
            32.9,
            36.2,
            33.5,
            31.2,
            25.3,
            14.9,
            13.7,
            22.3,
            22.0,
            26.3,
            26.2,
            27.2,
            29.0
        ],
        "winddirection_10m": [
            87,
            85,
            84,
            83,
            84,
            84,
            83,
            83,
            86,
            79,
            77,
            77,
            81,
            76,
            57,
            54,
            108,
            148,
            188,
            179,
            143,
            147,
            167,
            154
        ],
        "winddirection_100m": [
            87,
            85,
            84,
            84,
            83,
            85,
            83,
            83,
            86,
            79,
            76,
            77,
            80,
            75,
            56,
            54,
            110,
            157,
            189,
            181,
            147,
            153,
            173,
            160
        ],
        "windgusts_10m": [
            52.2,
            51.8,
            51.5,
            52.6,
            51.5,
            50.4,
            51.8,
            54.4,
            62.3,
            62.6,
            60.8,
            58.0,
            56.9,
            54.0,
            45.0,
            35.3,
            32.4,
            28.1,
            33.5,
            42.1,
            44.3,
            37.4,
            36.7,
            38.2
        ],
        "soil_temperature_0_to_7cm": [
            29.1,
            29.4,
            29.3,
            29.1,
            29.0,
            29.1,
            29.0,
            28.9,
            28.8,
            28.7,
            28.7,
            28.8,
            28.9,
            28.7,
            28.4,
            28.5,
            28.1,
            27.7,
            27.7,
            27.7,
            27.6,
            27.5,
            27.8,
            27.6
        ],
        "soil_temperature_7_to_28cm": [
            28.9,
            28.9,
            28.8,
            28.8,
            28.7,
            28.7,
            28.6,
            28.6,
            28.5,
            28.5,
            28.4,
            28.4,
            28.3,
            28.3,
            28.2,
            28.1,
            28.1,
            28.1,
            28.1,
            28.1,
            28.1,
            28.0,
            28.2,
            28.2
        ],
        "soil_temperature_28_to_100cm": [
            28.7,
            28.7,
            28.7,
            28.7,
            28.7,
            28.7,
            28.7,
            28.7,
            28.7,
            28.7,
            28.6,
            28.6,
            28.6,
            28.6,
            28.6,
            28.6,
            28.6,
            28.6,
            28.6,
            28.6,
            28.6,
            28.6,
            28.6,
            28.6
        ],
        "soil_temperature_100_to_255cm": [
            28.1,
            28.1,
            28.1,
            28.1,
            28.1,
            28.1,
            28.1,
            28.1,
            28.1,
            28.1,
            28.1,
            28.1,
            28.1,
            28.1,
            28.1,
            28.1,
            28.1,
            28.1,
            28.1,
            28.1,
            28.1,
            28.1,
            28.1,
            28.1
        ],
        "soil_moisture_0_to_7cm": [
            0.158,
            0.157,
            0.157,
            0.157,
            0.157,
            0.157,
            0.157,
            0.159,
            0.164,
            0.165,
            0.164,
            0.172,
            0.178,
            0.188,
            0.207,
            0.227,
            0.238,
            0.242,
            0.259,
            0.269,
            0.273,
            0.287,
            0.273,
            0.274
        ],
        "soil_moisture_7_to_28cm": [
            0.149,
            0.149,
            0.149,
            0.149,
            0.149,
            0.149,
            0.149,
            0.149,
            0.149,
            0.149,
            0.149,
            0.149,
            0.149,
            0.149,
            0.149,
            0.149,
            0.15,
            0.15,
            0.151,
            0.152,
            0.154,
            0.157,
            0.156,
            0.158
        ],
        "soil_moisture_28_to_100cm": [
            0.16,
            0.16,
            0.16,
            0.16,
            0.16,
            0.16,
            0.16,
            0.16,
            0.16,
            0.16,
            0.159,
            0.159,
            0.159,
            0.159,
            0.159,
            0.159,
            0.159,
            0.159,
            0.159,
            0.159,
            0.159,
            0.159,
            0.16,
            0.16
        ],
        "soil_moisture_100_to_255cm": [
            0.191,
            0.191,
            0.191,
            0.191,
            0.191,
            0.191,
            0.191,
            0.191,
            0.191,
            0.191,
            0.191,
            0.191,
            0.191,
            0.191,
            0.191,
            0.191,
            0.191,
            0.191,
            0.191,
            0.191,
            0.191,
            0.191,
            0.191,
            0.191
        ]
    }
}