{
    "latitude": 39.300003,
    "longitude": -61.9,
    "generationtime_ms": 0.4329681396484375,
    "utc_offset_seconds": 0,
    "timezone": "GMT",
    "timezone_abbreviation": "GMT",
    "elevation": 0.0,
    "hourly_units": {
        "time": "iso8601",
        "temperature_2m": "°C",
        "relativehumidity_2m": "%",
        "dewpoint_2m": "°C",
        "apparent_temperature": "°C",
        "precipitation": "mm",
        "rain": "mm",
        "snowfall": "cm",
        "snow_depth": "m",
        "weathercode": "wmo code",
        "pressure_msl": "hPa",
        "surface_pressure": "hPa",
        "cloudcover": "%",
        "cloudcover_low": "%",
        "cloudcover_mid": "%",
        "cloudcover_high": "%",
        "et0_fao_evapotranspiration": "mm",
        "vapor_pressure_deficit": "kPa",
        "windspeed_10m": "km/h",
        "windspeed_100m": "km/h",
        "winddirection_10m": "°",
        "winddirection_100m": "°",
        "windgusts_10m": "km/h",
        "soil_temperature_0_to_7cm": "°C",
        "soil_temperature_7_to_28cm": "°C",
        "soil_temperature_28_to_100cm": "°C",
        "soil_temperature_100_to_255cm": "°C",
        "soil_moisture_0_to_7cm": "m³/m³",
        "soil_moisture_7_to_28cm": "m³/m³",
        "soil_moisture_28_to_100cm": "m³/m³",
        "soil_moisture_100_to_255cm": "m³/m³"
    },
    "hourly": {
        "time": [
            "1995-09-21T00:00",
            "1995-09-21T01:00",
            "1995-09-21T02:00",
            "1995-09-21T03:00",
            "1995-09-21T04:00",
            "1995-09-21T05:00",
            "1995-09-21T06:00",
            "1995-09-21T07:00",
            "1995-09-21T08:00",
            "1995-09-21T09:00",
            "1995-09-21T10:00",
            "1995-09-21T11:00",
            "1995-09-21T12:00",
            "1995-09-21T13:00",
            "1995-09-21T14:00",
            "1995-09-21T15:00",
            "1995-09-21T16:00",
            "1995-09-21T17:00",
            "1995-09-21T18:00",
            "1995-09-21T19:00",
            "1995-09-21T20:00",
            "1995-09-21T21:00",
            "1995-09-21T22:00",
            "1995-09-21T23:00"
        ],
        "temperature_2m": [
            24.5,
            24.5,
            24.5,
            24.5,
            24.5,
            24.6,
            24.8,
            24.9,
            24.8,
            24.9,
            24.8,
            24.8,
            24.8,
            24.5,
            24.4,
            24.4,
            24.2,
            24.2,
            24.1,
            24.0,
            23.9,
            23.7,
            22.9,
            22.7
        ],
        "relativehumidity_2m": [
            88,
            88,
            90,
            91,
            90,
            90,
            90,
            91,
            92,
            92,
            91,
            90,
            90,
            90,
            90,
            89,
            89,
            89,
            89,
            90,
            90,
            91,
            91,
            91
        ],
        "dewpoint_2m": [
            22.4,
            22.4,
            22.8,
            22.9,
            22.9,
            22.9,
            23.0,
            23.2,
            23.4,
            23.5,
            23.2,
            23.1,
            23.0,
            22.8,
            22.6,
            22.5,
            22.4,
            22.2,
            22.2,
            22.2,
            22.1,
            22.1,
            21.4,
            21.2
        ],
        "apparent_temperature": [
            20.0,
            19.6,
            19.2,
            18.9,
            20.3,
            22.1,
            24.9,
            29.3,
            27.4,
            24.7,
            23.1,
            22.1,
            21.5,
            21.2,
            21.2,
            21.4,
            21.4,
            21.3,
            21.4,
            21.5,
            21.6,
            21.7,
            20.9,
            20.4
        ],
        "precipitation": [
            3.8,
            2.1,
            2.5,
            6.3,
            7.4,
            3.6,
            1.6,
            0.3,
            0.0,
            0.0,
            0.0,
            0.0,
            0.0,
            0.0,
            0.0,
            0.0,
            0.0,
            0.0,
            0.0,
            0.0,
            0.0,
            0.0,
            0.2,
            0.2
        ],
        "rain": [
            3.8,
            2.1,
            2.5,
            6.3,
            7.4,
            3.6,
            1.6,
            0.3,
            0.0,
            0.0,
            0.0,
            0.0,
            0.0,
            0.0,
            0.0,
            0.0,
            0.0,
            0.0,
            0.0,
            0.0,
            0.0,
            0.0,
            0.2,
            0.2
        ],
        "snowfall": [
            0.0,
            0.0,
            0.0,
            0.0,
            0.0,
            0.0,
            0.0,
            0.0,
            0.0,
            0.0,
            0.0,
            0.0,
            0.0,
            0.0,
            0.0,
            0.0,
            0.0,
            0.0,
            0.0,
            0.0,
            0.0,
            0.0,
            0.0,
            0.0
        ],
        "snow_depth": [
            null,
            null,
            null,
            null,
            null,
            null,
            null,
            null,
            null,
            null,
            null,
            null,
            null,
            null,
            null,
            null,
            null,
            null,
            null,
            null,
            null,
            null,
            null,
            null
        ],
        "weathercode": [
            63,
            61,
            63,
            63,
            63,
            63,
            61,
            51,
            3,
            3,
            3,
            3,
            3,
            3,
            3,
            3,
            3,
            2,
            2,
            3,
            3,
            3,
            51,
            51
        ],
        "pressure_msl": [
            1002.5,
            1000.8,
            998.6,
            995.5,
            992.2,
            990.2,
            988.0,
            987.0,
            987.2,
            988.6,
            990.0,
            992.2,
            995.2,
            997.4,
            999.5,
            1001.3,
            1002.0,
            1003.0,
            1003.7,
            1004.6,
            1005.6,
            1006.3,
            1007.6,
            1008.6
        ],
        "surface_pressure": [
            1002.5,
            1000.8,
            998.6,
            995.5,
            992.2,
            990.2,
            988.0,
            987.0,
            987.2,
            988.6,
            990.0,
            992.2,
            995.2,
            997.4,
            999.5,
            1001.3,
            1002.0,
            1003.0,
            1003.7,
            1004.6,
            1005.6,
            1006.3,
            1007.6,
            1008.6
        ],
        "cloudcover": [
            100,
            100,
            100,
            100,
            100,
            100,
            100,
            100,
            100,
            85,
            100,
            100,
            100,
            100,
            100,
            100,
            98,
            76,
            72,
            90,
            90,
            90,
            94,
            90
        ],
        "cloudcover_low": [
            93,
            87,
            80,
            97,
            99,
            97,
            99,
            80,
            84,
            59,
            99,
            90,
            100,
            99,
            100,
            98,
            95,
            82,
            80,
            99,
            100,
            100,
            100,
            100
        ],
        "cloudcover_mid": [
            98,
            92,
            100,
            100,
            98,
            98,
            66,
            26,
            7,
            3,
            0,
            0,
            0,
            0,
            0,
            0,
            0,
            0,
            0,
            1,
            0,
            0,
            6,
            0
        ],
        "cloudcover_high": [
            98,
            90,
            99,
            99,
            97,
            95,
            99,
            100,
            100,
            100,
            100,
            100,
            100,
            100,
            95,
            77,
            41,
            8,
            0,
            0,
            0,
            0,
            0,
            0
        ],
        "et0_fao_evapotranspiration": [
            0.07,
            0.07,
            0.06,
            0.06,
            0.05,
            0.05,
            0.04,
            0.0,
            0.01,
            0.03,
            0.04,
            0.07,
            0.09,
            0.11,
            0.13,
            0.16,
            0.2,
            0.2,
            0.22,
            0.17,
            0.1,
            0.08,
            0.05,
            0.03
        ],
        "vapor_pressure_deficit": [
            0.37,
            0.36,
            0.3,
            0.29,
            0.3,
            0.32,
            0.31,
            0.3,
            0.25,
            0.25,
            0.27,
            0.3,
            0.32,
            0.31,
            0.31,
            0.32,
            0.33,
            0.34,
            0.32,
            0.31,
            0.29,
            0.27,
            0.24,
            0.24
        ],
        "windspeed_10m": [
            66.2,
            68.9,
            72.8,
            75.2,
            65.9,
            54.5,
            36.9,
            8.3,
            21.4,
            41.3,
            50.1,
            56.8,
            60.1,
            59.9,
            58.2,
            55.7,
            54.6,
            54.7,
            53.3,
            51.4,
            49.6,
            48.0,
            44.8,
            46.7
        ],
        "windspeed_100m": [
            89.4,
            93.1,
            98.3,
            101.2,
            88.1,
            71.4,
            48.5,
            12.1,
            24.9,
            48.5,
            59.0,
            69.5,
            76.1,
            76.4,
            74.9,
            71.9,
            69.6,
            68.4,
            66.5,
            63.4,
            60.1,
            57.3,
            54.1,
            55.3
        ],
        "winddirection_10m": [
            135,
            138,
            135,
            138,
            148,
            162,
            161,
            182,
            306,
            318,
            326,
            333,
            333,
            334,
            332,
            329,
            329,
            330,
            333,
            336,
            338,
            340,
            336,
            340
        ],
        "winddirection_100m": [
            137,
            140,
            137,
            140,
            151,
            164,
            167,
            190,
            309,
            320,
            329,
            336,
            336,
            336,
            333,
            331,
            331,
            332,
            335,
            338,
            340,
            342,
            339,
            342
        ],
        "windgusts_10m": [
            92.2,
            95.0,
            103.0,
            110.2,
            113.4,
            107.3,
            99.0,
            49.0,
            37.1,
            52.9,
            66.6,
            77.0,
            83.9,
            86.4,
            85.0,
            82.8,
            79.2,
            74.9,
            71.3,
            73.1,
            69.5,
            65.9,
            63.4,
            63.0
        ],
        "soil_temperature_0_to_7cm": [
            24.6,
            24.6,
            24.6,
            24.6,
            24.6,
            24.6,
            24.6,
            24.6,
            24.6,
            24.6,
            24.6,
            24.6,
            24.6,
            24.6,
            24.6,
            24.6,
            24.6,
            24.6,
            24.6,
            24.6,
            24.6,
            24.6,
            24.8,
            24.8
        ],
        "soil_temperature_7_to_28cm": [
            24.9,
            24.9,
            24.9,
            24.9,
            24.9,
            24.9,
            24.9,
            24.9,
            24.9,
            24.9,
            24.6,
            24.6,
            24.6,
            24.6,
            24.6,
            24.6,
            24.6,
            24.6,
            24.6,
            24.6,
            24.6,
            24.6,
            24.6,
            24.6
        ],
        "soil_temperature_28_to_100cm": [
            24.9,
            24.9,
            24.9,
            24.9,
            24.9,
            24.9,
            24.9,
            24.9,
            24.9,
            24.9,
            24.6,
            24.6,
            24.6,
            24.6,
            24.6,
            24.6,
            24.6,
            24.6,
            24.6,
            24.6,
            24.6,
            24.6,
            24.6,
            24.6
        ],
        "soil_temperature_100_to_255cm": [
            24.9,
            24.9,
            24.9,
            24.9,
            24.9,
            24.9,
            24.9,
            24.9,
            24.9,
            24.9,
            24.6,
            24.6,
            24.6,
            24.6,
            24.6,
            24.6,
            24.6,
            24.6,
            24.6,
            24.6,
            24.6,
            24.6,
            24.6,
            24.6
        ],
        "soil_moisture_0_to_7cm": [
            0.0,
            0.0,
            0.0,
            0.0,
            0.0,
            0.0,
            0.0,
            0.0,
            0.0,
            0.0,
            0.0,
            0.0,
            0.0,
            0.0,
            0.0,
            0.0,
            0.0,
            0.0,
            0.0,
            0.0,
            0.0,
            0.0,
            0.0,
            0.0
        ],
        "soil_moisture_7_to_28cm": [
            0.0,
            0.0,
            0.0,
            0.0,
            0.0,
            0.0,
            0.0,
            0.0,
            0.0,
            0.0,
            0.0,
            0.0,
            0.0,
            0.0,
            0.0,
            0.0,
            0.0,
            0.0,
            0.0,
            0.0,
            0.0,
            0.0,
            0.0,
            0.0
        ],
        "soil_moisture_28_to_100cm": [
            0.0,
            0.0,
            0.0,
            0.0,
            0.0,
            0.0,
            0.0,
            0.0,
            0.0,
            0.0,
            0.0,
            0.0,
            0.0,
            0.0,
            0.0,
            0.0,
            0.0,
            0.0,
            0.0,
            0.0,
            0.0,
            0.0,
            0.0,
            0.0
        ],
        "soil_moisture_100_to_255cm": [
            0.0,
            0.0,
            0.0,
            0.0,
            0.0,
            0.0,
            0.0,
            0.0,
            0.0,
            0.0,
            0.0,
            0.0,
            0.0,
            0.0,
            0.0,
            0.0,
            0.0,
            0.0,
            0.0,
            0.0,
            0.0,
            0.0,
            0.0,
            0.0
        ]
    }
}